cli/alarm.py
lztools/utils/alarm.py
lztools.alarm-0.0.3.dist-info/LICENSE.txt
lztools.alarm-0.0.3.dist-info/METADATA
lztools.alarm-0.0.3.dist-info/RECORD
lztools.alarm-0.0.3.dist-info/WHEEL
lztools.alarm-0.0.3.dist-info/entry_points.txt
lztools.alarm-0.0.3.dist-info/top_level.txt
