Metadata-Version: 2.1
Name: lztools.alarm
Version: 0.0.3
Summary: A collection of useful utilities by Laz, ᒪᗩᘔ, ㄥ卂乙, ןɐz, lคz, ℓДՀ, լᕱᏃ, Նคઽ, ﾚﾑ乙
Home-page: UNKNOWN
Author: Laz aka Zanzes
Author-email: ubuntuea@gmail.com
License: MIT License
Platform: UNKNOWN
Classifier: Development Status :: 3 - Alpha
Classifier: Intended Audience :: Developers
Classifier: Topic :: System :: Systems Administration
Classifier: License :: OSI Approved :: MIT License
Classifier: Programming Language :: Python :: 3.7
